{"MI/y5vTS/oaV3mVfdLhhYQ==":"mbr.jpg","RySyrkUrrPZPhzdrNWLxhg==":"mbr.jpeg","IedBUMFPy/wdQmKABiOf4g==":"mbr-1.jpg","X30aVRBEqsZY/bFEWmkiVg==":"mbr-2.jpg","YNiXBWgwNOjqA22Dmwqb5g==":"mbr-3.jpg","DrFPsfmeg5oSTFbYnhLeYw==":"mbr-4.jpg","6OY4DwgD2obALVw0F7NFIw==":"mbr-5.jpg","uEGJd4PrLTvFpgfDvYs4Lg==":"mbr-6.jpg","XRDdhODpZEaMtrsqfQDByg==":"mbr-7.jpg","+CFTCwDQuqe5qZvoVm36lQ==":"mbr-8.jpg","2Nk/Iz1/Q+zR+CCo2aoFbQ==":"screenshot-20241117-103336-instagram.jpg","hKKw2Ki+XmClNOk81XJC+w==":"20241117-101512.png","fqNNttW7OhqhRxMB6cEk1Q==":"mbr-1.jpg","cXjT0tXt4XihVHV3DfIP7A==":"mbr-3.jpg","fMTjpu/RmLiC0+eQ3p0MbA==":"mbr-4.jpg","CVuaOvWr55S08gbp8jQL+g==":"screenshot-20241117-114557-facebook.jpg","/uK1wl48MhtbSGGKhGqM0A==":"screenshot-20241117-114430-facebook.jpg","3oI4miVKM2VFTjEC5RQ2ow==":"screenshot-20241117-114557-facebook.jpeg","txlvdluEloZScZivZ9v/EA==":"mbr-8.jpg","NKes7+N3jpOkvvmbXNv6Jw==":"mbr.png","G7910Io9H/WUSOYZqvee8A==":"team1.jpeg"}